[
  {
    "id": 1,
    "name": "dff",
    "schedule_id": 1,
    "worker_id": 1,
    "status": "failed",
    "created_at": "2026-01-25T10:00:00"
  },
  {
    "id": 2,
    "name": "dff",
    "schedule_id": 1,
    "worker_id": 2,
    "status": "failed",
    "created_at": "2026-01-29T21:01:54.742903",
    "started_at": null,
    "finished_at": null
  },
  {
    "id": 3,
    "name": "dff",
    "schedule_id": 1,
    "worker_id": 2,
    "status": "completed",
    "created_at": "2026-01-30T13:50:56.035865",
    "started_at": null,
    "finished_at": null
  },
  {
    "id": 4,
    "name": "dff",
    "schedule_id": 2,
    "worker_id": 2,
    "status": "completed",
    "created_at": "2026-01-30T13:50:56.048626",
    "started_at": null,
    "finished_at": null
  },
  {
    "id": 5,
    "name": "dff",
    "schedule_id": 1,
    "worker_id": 2,
    "status": "completed",
    "created_at": "2026-01-30T13:51:06.077438",
    "started_at": null,
    "finished_at": null
  },
  {
    "id": 6,
    "name": "dff",
    "schedule_id": 1,
    "worker_id": 2,
    "status": "completed",
    "created_at": "2026-01-30T13:52:06.185688",
    "started_at": null,
    "finished_at": null
  },
  {
    "id": 7,
    "name": "dff",
    "schedule_id": 2,
    "worker_id": 2,
    "status": "completed",
    "created_at": "2026-01-30T13:52:06.205152",
    "started_at": null,
    "finished_at": null
  },
  {
    "id": 8,
    "name": "dff",
    "schedule_id": 1,
    "worker_id": 2,
    "status": "completed",
    "created_at": "2026-01-30T13:55:39.610388",
    "started_at": null,
    "finished_at": null
  },
  {
    "id": 9,
    "name": "dff",
    "schedule_id": 2,
    "worker_id": 2,
    "status": "completed",
    "created_at": "2026-01-30T13:55:39.633362",
    "started_at": null,
    "finished_at": null
  },
  {
    "id": 10,
    "name": "dff",
    "schedule_id": 1,
    "worker_id": 2,
    "status": "completed",
    "created_at": "2026-01-30T13:56:05.223633",
    "started_at": null,
    "finished_at": null
  },
  {
    "id": 11,
    "name": "dff",
    "schedule_id": 2,
    "worker_id": 2,
    "status": "completed",
    "created_at": "2026-01-30T13:56:05.238334",
    "started_at": null,
    "finished_at": null
  },
  {
    "id": 12,
    "name": "dff",
    "schedule_id": 1,
    "worker_id": 1,
    "status": "pending",
    "created_at": "2026-01-30T13:57:05.336228",
    "started_at": null,
    "finished_at": null
  },
  {
    "id": 13,
    "name": "dff",
    "schedule_id": 1,
    "worker_id": 2,
    "status": "completed",
    "created_at": "2026-01-30T13:58:05.433727",
    "started_at": null,
    "finished_at": null
  },
  {
    "id": 14,
    "name": "dff",
    "schedule_id": 2,
    "worker_id": 2,
    "status": "completed",
    "created_at": "2026-01-30T13:58:05.451173",
    "started_at": null,
    "finished_at": null
  },
  {
    "id": 15,
    "name": "dff",
    "schedule_id": 1,
    "worker_id": 1,
    "status": "pending",
    "created_at": "2026-01-30T13:59:05.531413",
    "started_at": null,
    "finished_at": null
  },
  {
    "id": 16,
    "name": "XSS - http://testphp.vulnweb.com/search.php",
    "schedule_id": 1,
    "worker_id": 2,
    "status": "completed",
    "created_at": "2026-01-30T15:22:18.029698",
    "started_at": "2026-01-30 08:22:24.178799+00:00",
    "finished_at": "2026-01-30 08:30:56.105995+00:00"
  },
  {
    "id": 17,
    "name": "SQL_INJECTION - www.test.test.xyz",
    "schedule_id": 2,
    "worker_id": 2,
    "status": "completed",
    "created_at": "2026-01-30T15:22:18.048711",
    "started_at": "2026-01-30 08:22:26.257851+00:00",
    "finished_at": "2026-01-30 08:22:27.181475+00:00"
  }
]